{
  "asOf": "2026-07-12",
  "timezone": "America/Los_Angeles",
  "generatedAtUtc": "2026-07-13T05:23:12+00:00",
  "windows": {
    "day": {
      "start": "2026-07-12",
      "end": "2026-07-12",
      "label": "Sun, Jul 12"
    },
    "week": {
      "start": "2026-07-06",
      "end": "2026-07-12",
      "label": "Jul 6 - Jul 12"
    },
    "month": {
      "start": "2026-07-01",
      "end": "2026-07-31",
      "label": "July 2026"
    },
    "quarter": {
      "start": "2026-07-01",
      "end": "2026-09-30",
      "label": "Q3 2026"
    },
    "allTime": {
      "start": "2026-06-15",
      "end": "2026-07-12",
      "label": "Since launch, Jun 15"
    }
  },
  "roster": [
    {
      "key": "caleb",
      "name": "Caleb Chase"
    },
    {
      "key": "carlos",
      "name": "Carlos Fierro"
    },
    {
      "key": "james",
      "name": "James Wellington"
    }
  ],
  "rosterNames": "Caleb Chase, Carlos Fierro, James Wellington",
  "leaderboard": {
    "day": [
      {
        "key": "caleb",
        "name": "Caleb Chase",
        "status": "active",
        "dealsClosed": 0,
        "cash": "$0.00",
        "cashCents": 0,
        "callsBooked": 10,
        "callsHeld": 0,
        "noShow": 1,
        "noShowRate": "14%",
        "showed": 6,
        "showRate": "86%",
        "showRateNum": 85.71428571428571,
        "closeRate": "0%",
        "closeRateNum": 0.0,
        "outboundCalls": 0,
        "inboundCalls": 0,
        "totalCalls": 0,
        "callHours": 0.0,
        "rank": 1,
        "trend": "flat",
        "trendNote": "flat vs prior period",
        "badges": [
          "Top Closer",
          "First Deal",
          "Best Show Rate",
          "Most Booked"
        ],
        "gapNote": "No cash collected yet this window"
      },
      {
        "key": "carlos",
        "name": "Carlos Fierro",
        "status": "active",
        "dealsClosed": 0,
        "cash": "$0.00",
        "cashCents": 0,
        "callsBooked": 6,
        "callsHeld": 0,
        "noShow": 0,
        "noShowRate": "awaiting",
        "showed": 0,
        "showRate": "awaiting",
        "showRateNum": null,
        "closeRate": "awaiting",
        "closeRateNum": null,
        "outboundCalls": 0,
        "inboundCalls": 0,
        "totalCalls": 0,
        "callHours": 0.0,
        "rank": 2,
        "trend": "flat",
        "trendNote": "flat vs prior period",
        "badges": [],
        "gapNote": "No cash collected yet this window"
      },
      {
        "key": "james",
        "name": "James Wellington",
        "status": "active",
        "dealsClosed": 0,
        "cash": "$0.00",
        "cashCents": 0,
        "callsBooked": 0,
        "callsHeld": 0,
        "noShow": 0,
        "noShowRate": "awaiting",
        "showed": 0,
        "showRate": "awaiting",
        "showRateNum": null,
        "closeRate": "awaiting",
        "closeRateNum": null,
        "outboundCalls": 0,
        "inboundCalls": 0,
        "totalCalls": 0,
        "callHours": 0.0,
        "rank": 3,
        "trend": "flat",
        "trendNote": "flat vs prior period",
        "badges": [],
        "gapNote": "No cash collected yet this window"
      }
    ],
    "week": [
      {
        "key": "caleb",
        "name": "Caleb Chase",
        "status": "active",
        "dealsClosed": 0,
        "cash": "$0.00",
        "cashCents": 0,
        "callsBooked": 63,
        "callsHeld": 0,
        "noShow": 19,
        "noShowRate": "54%",
        "showed": 16,
        "showRate": "46%",
        "showRateNum": 45.714285714285715,
        "closeRate": "0%",
        "closeRateNum": 0.0,
        "outboundCalls": 43,
        "inboundCalls": 8,
        "totalCalls": 51,
        "callHours": 1.4,
        "rank": 1,
        "trend": "down",
        "trendNote": "-$4,997.00, -1 deal",
        "badges": [
          "Top Closer",
          "First Deal",
          "Most Active",
          "Most Booked"
        ],
        "gapNote": "No cash collected yet this window"
      },
      {
        "key": "carlos",
        "name": "Carlos Fierro",
        "status": "active",
        "dealsClosed": 0,
        "cash": "$0.00",
        "cashCents": 0,
        "callsBooked": 32,
        "callsHeld": 0,
        "noShow": 3,
        "noShowRate": "50%",
        "showed": 3,
        "showRate": "50%",
        "showRateNum": 50.0,
        "closeRate": "0%",
        "closeRateNum": 0.0,
        "outboundCalls": 0,
        "inboundCalls": 0,
        "totalCalls": 0,
        "callHours": 0.0,
        "rank": 2,
        "trend": "flat",
        "trendNote": "flat vs prior period",
        "badges": [
          "Best Show Rate"
        ],
        "gapNote": "No cash collected yet this window"
      },
      {
        "key": "james",
        "name": "James Wellington",
        "status": "active",
        "dealsClosed": 0,
        "cash": "$0.00",
        "cashCents": 0,
        "callsBooked": 0,
        "callsHeld": 0,
        "noShow": 0,
        "noShowRate": "awaiting",
        "showed": 0,
        "showRate": "awaiting",
        "showRateNum": null,
        "closeRate": "awaiting",
        "closeRateNum": null,
        "outboundCalls": 0,
        "inboundCalls": 0,
        "totalCalls": 0,
        "callHours": 0.0,
        "rank": 3,
        "trend": "flat",
        "trendNote": "flat vs prior period",
        "badges": [],
        "gapNote": "No cash collected yet this window"
      }
    ],
    "month": [
      {
        "key": "caleb",
        "name": "Caleb Chase",
        "status": "active",
        "dealsClosed": 0,
        "cash": "$0.00",
        "cashCents": 0,
        "callsBooked": 65,
        "callsHeld": 0,
        "noShow": 20,
        "noShowRate": "56%",
        "showed": 16,
        "showRate": "44%",
        "showRateNum": 44.44444444444444,
        "closeRate": "0%",
        "closeRateNum": 0.0,
        "outboundCalls": 58,
        "inboundCalls": 8,
        "totalCalls": 66,
        "callHours": 1.5,
        "rank": 1,
        "trend": "down",
        "trendNote": "-$4,997.00, -1 deal",
        "badges": [
          "Top Closer",
          "First Deal",
          "Most Active",
          "Most Booked"
        ],
        "gapNote": "No cash collected yet this window"
      },
      {
        "key": "carlos",
        "name": "Carlos Fierro",
        "status": "active",
        "dealsClosed": 0,
        "cash": "$0.00",
        "cashCents": 0,
        "callsBooked": 39,
        "callsHeld": 1,
        "noShow": 6,
        "noShowRate": "50%",
        "showed": 6,
        "showRate": "50%",
        "showRateNum": 50.0,
        "closeRate": "0%",
        "closeRateNum": 0.0,
        "outboundCalls": 0,
        "inboundCalls": 0,
        "totalCalls": 0,
        "callHours": 0.0,
        "rank": 2,
        "trend": "flat",
        "trendNote": "flat vs prior period",
        "badges": [
          "Best Show Rate"
        ],
        "gapNote": "No cash collected yet this window"
      },
      {
        "key": "james",
        "name": "James Wellington",
        "status": "active",
        "dealsClosed": 0,
        "cash": "$0.00",
        "cashCents": 0,
        "callsBooked": 0,
        "callsHeld": 0,
        "noShow": 0,
        "noShowRate": "awaiting",
        "showed": 0,
        "showRate": "awaiting",
        "showRateNum": null,
        "closeRate": "awaiting",
        "closeRateNum": null,
        "outboundCalls": 0,
        "inboundCalls": 0,
        "totalCalls": 0,
        "callHours": 0.0,
        "rank": 3,
        "trend": "flat",
        "trendNote": "flat vs prior period",
        "badges": [],
        "gapNote": "No cash collected yet this window"
      }
    ],
    "quarter": [
      {
        "key": "caleb",
        "name": "Caleb Chase",
        "status": "active",
        "dealsClosed": 0,
        "cash": "$0.00",
        "cashCents": 0,
        "callsBooked": 65,
        "callsHeld": 0,
        "noShow": 20,
        "noShowRate": "56%",
        "showed": 16,
        "showRate": "44%",
        "showRateNum": 44.44444444444444,
        "closeRate": "0%",
        "closeRateNum": 0.0,
        "outboundCalls": 58,
        "inboundCalls": 8,
        "totalCalls": 66,
        "callHours": 1.5,
        "rank": 1,
        "trend": "down",
        "trendNote": "-$4,997.00, -1 deal",
        "badges": [
          "Top Closer",
          "First Deal",
          "Most Active",
          "Most Booked"
        ],
        "gapNote": "No cash collected yet this window"
      },
      {
        "key": "carlos",
        "name": "Carlos Fierro",
        "status": "active",
        "dealsClosed": 0,
        "cash": "$0.00",
        "cashCents": 0,
        "callsBooked": 39,
        "callsHeld": 1,
        "noShow": 6,
        "noShowRate": "50%",
        "showed": 6,
        "showRate": "50%",
        "showRateNum": 50.0,
        "closeRate": "0%",
        "closeRateNum": 0.0,
        "outboundCalls": 0,
        "inboundCalls": 0,
        "totalCalls": 0,
        "callHours": 0.0,
        "rank": 2,
        "trend": "flat",
        "trendNote": "flat vs prior period",
        "badges": [
          "Best Show Rate"
        ],
        "gapNote": "No cash collected yet this window"
      },
      {
        "key": "james",
        "name": "James Wellington",
        "status": "active",
        "dealsClosed": 0,
        "cash": "$0.00",
        "cashCents": 0,
        "callsBooked": 0,
        "callsHeld": 0,
        "noShow": 0,
        "noShowRate": "awaiting",
        "showed": 0,
        "showRate": "awaiting",
        "showRateNum": null,
        "closeRate": "awaiting",
        "closeRateNum": null,
        "outboundCalls": 0,
        "inboundCalls": 0,
        "totalCalls": 0,
        "callHours": 0.0,
        "rank": 3,
        "trend": "flat",
        "trendNote": "flat vs prior period",
        "badges": [],
        "gapNote": "No cash collected yet this window"
      }
    ],
    "allTime": [
      {
        "key": "caleb",
        "name": "Caleb Chase",
        "status": "active",
        "dealsClosed": 1,
        "cash": "$4,997.00",
        "cashCents": 499700,
        "callsBooked": 70,
        "callsHeld": 0,
        "noShow": 23,
        "noShowRate": "58%",
        "showed": 17,
        "showRate": "42%",
        "showRateNum": 42.5,
        "closeRate": "6%",
        "closeRateNum": 5.882352941176471,
        "outboundCalls": 68,
        "inboundCalls": 12,
        "totalCalls": 80,
        "callHours": 1.9,
        "rank": 1,
        "trend": "na",
        "trendNote": "since launch, no prior period",
        "badges": [
          "Leading",
          "Top Closer",
          "First Deal",
          "Most Active",
          "Most Booked"
        ],
        "gapNote": "Leading by $4,997.00"
      },
      {
        "key": "carlos",
        "name": "Carlos Fierro",
        "status": "active",
        "dealsClosed": 0,
        "cash": "$0.00",
        "cashCents": 0,
        "callsBooked": 49,
        "callsHeld": 2,
        "noShow": 8,
        "noShowRate": "50%",
        "showed": 8,
        "showRate": "50%",
        "showRateNum": 50.0,
        "closeRate": "0%",
        "closeRateNum": 0.0,
        "outboundCalls": 0,
        "inboundCalls": 0,
        "totalCalls": 0,
        "callHours": 0.0,
        "rank": 2,
        "trend": "na",
        "trendNote": "since launch, no prior period",
        "badges": [
          "Best Show Rate"
        ],
        "gapNote": "$4,997.00 to pass Caleb Chase"
      },
      {
        "key": "james",
        "name": "James Wellington",
        "status": "active",
        "dealsClosed": 0,
        "cash": "$0.00",
        "cashCents": 0,
        "callsBooked": 0,
        "callsHeld": 0,
        "noShow": 0,
        "noShowRate": "awaiting",
        "showed": 0,
        "showRate": "awaiting",
        "showRateNum": null,
        "closeRate": "awaiting",
        "closeRateNum": null,
        "outboundCalls": 10,
        "inboundCalls": 0,
        "totalCalls": 10,
        "callHours": 0.0,
        "rank": 3,
        "trend": "na",
        "trendNote": "since launch, no prior period",
        "badges": [],
        "gapNote": "$4,997.00 to pass Caleb Chase"
      }
    ]
  },
  "leaderboardAll": {
    "day": [
      {
        "key": "caleb",
        "name": "Caleb Chase",
        "status": "active",
        "dealsClosed": 0,
        "cash": "$0.00",
        "cashCents": 0,
        "callsBooked": 10,
        "callsHeld": 0,
        "noShow": 1,
        "noShowRate": "14%",
        "showed": 6,
        "showRate": "86%",
        "showRateNum": 85.71428571428571,
        "closeRate": "0%",
        "closeRateNum": 0.0,
        "outboundCalls": 0,
        "inboundCalls": 0,
        "totalCalls": 0,
        "callHours": 0.0,
        "rank": 1,
        "trend": "flat",
        "trendNote": "flat vs prior period"
      },
      {
        "key": "carlos",
        "name": "Carlos Fierro",
        "status": "active",
        "dealsClosed": 0,
        "cash": "$0.00",
        "cashCents": 0,
        "callsBooked": 6,
        "callsHeld": 0,
        "noShow": 0,
        "noShowRate": "awaiting",
        "showed": 0,
        "showRate": "awaiting",
        "showRateNum": null,
        "closeRate": "awaiting",
        "closeRateNum": null,
        "outboundCalls": 0,
        "inboundCalls": 0,
        "totalCalls": 0,
        "callHours": 0.0,
        "rank": 2,
        "trend": "flat",
        "trendNote": "flat vs prior period"
      },
      {
        "key": "james",
        "name": "James Wellington",
        "status": "active",
        "dealsClosed": 0,
        "cash": "$0.00",
        "cashCents": 0,
        "callsBooked": 0,
        "callsHeld": 0,
        "noShow": 0,
        "noShowRate": "awaiting",
        "showed": 0,
        "showRate": "awaiting",
        "showRateNum": null,
        "closeRate": "awaiting",
        "closeRateNum": null,
        "outboundCalls": 0,
        "inboundCalls": 0,
        "totalCalls": 0,
        "callHours": 0.0,
        "rank": 3,
        "trend": "flat",
        "trendNote": "flat vs prior period"
      },
      {
        "key": "dan",
        "name": "Dan Baldasso",
        "status": "offboarded",
        "dealsClosed": 0,
        "cash": "$0.00",
        "cashCents": 0,
        "callsBooked": 0,
        "callsHeld": 0,
        "noShow": 0,
        "noShowRate": "awaiting",
        "showed": 0,
        "showRate": "awaiting",
        "showRateNum": null,
        "closeRate": "awaiting",
        "closeRateNum": null,
        "outboundCalls": 0,
        "inboundCalls": 0,
        "totalCalls": 0,
        "callHours": 0.0,
        "trend": "flat",
        "trendNote": "flat vs prior period",
        "rank": 4
      },
      {
        "key": "matthew",
        "name": "Matthew Burns",
        "status": "offboarded",
        "dealsClosed": 0,
        "cash": "$0.00",
        "cashCents": 0,
        "callsBooked": 0,
        "callsHeld": 0,
        "noShow": 0,
        "noShowRate": "awaiting",
        "showed": 0,
        "showRate": "awaiting",
        "showRateNum": null,
        "closeRate": "awaiting",
        "closeRateNum": null,
        "outboundCalls": 0,
        "inboundCalls": 0,
        "totalCalls": 0,
        "callHours": 0.0,
        "trend": "flat",
        "trendNote": "flat vs prior period",
        "rank": 5
      }
    ],
    "week": [
      {
        "key": "caleb",
        "name": "Caleb Chase",
        "status": "active",
        "dealsClosed": 0,
        "cash": "$0.00",
        "cashCents": 0,
        "callsBooked": 63,
        "callsHeld": 0,
        "noShow": 19,
        "noShowRate": "54%",
        "showed": 16,
        "showRate": "46%",
        "showRateNum": 45.714285714285715,
        "closeRate": "0%",
        "closeRateNum": 0.0,
        "outboundCalls": 43,
        "inboundCalls": 8,
        "totalCalls": 51,
        "callHours": 1.4,
        "rank": 1,
        "trend": "down",
        "trendNote": "-$4,997.00, -1 deal"
      },
      {
        "key": "carlos",
        "name": "Carlos Fierro",
        "status": "active",
        "dealsClosed": 0,
        "cash": "$0.00",
        "cashCents": 0,
        "callsBooked": 32,
        "callsHeld": 0,
        "noShow": 3,
        "noShowRate": "50%",
        "showed": 3,
        "showRate": "50%",
        "showRateNum": 50.0,
        "closeRate": "0%",
        "closeRateNum": 0.0,
        "outboundCalls": 0,
        "inboundCalls": 0,
        "totalCalls": 0,
        "callHours": 0.0,
        "rank": 2,
        "trend": "flat",
        "trendNote": "flat vs prior period"
      },
      {
        "key": "james",
        "name": "James Wellington",
        "status": "active",
        "dealsClosed": 0,
        "cash": "$0.00",
        "cashCents": 0,
        "callsBooked": 0,
        "callsHeld": 0,
        "noShow": 0,
        "noShowRate": "awaiting",
        "showed": 0,
        "showRate": "awaiting",
        "showRateNum": null,
        "closeRate": "awaiting",
        "closeRateNum": null,
        "outboundCalls": 0,
        "inboundCalls": 0,
        "totalCalls": 0,
        "callHours": 0.0,
        "rank": 3,
        "trend": "flat",
        "trendNote": "flat vs prior period"
      },
      {
        "key": "dan",
        "name": "Dan Baldasso",
        "status": "offboarded",
        "dealsClosed": 0,
        "cash": "$0.00",
        "cashCents": 0,
        "callsBooked": 0,
        "callsHeld": 0,
        "noShow": 0,
        "noShowRate": "awaiting",
        "showed": 0,
        "showRate": "awaiting",
        "showRateNum": null,
        "closeRate": "awaiting",
        "closeRateNum": null,
        "outboundCalls": 15,
        "inboundCalls": 1,
        "totalCalls": 16,
        "callHours": 0.2,
        "trend": "flat",
        "trendNote": "flat vs prior period",
        "rank": 4
      },
      {
        "key": "matthew",
        "name": "Matthew Burns",
        "status": "offboarded",
        "dealsClosed": 0,
        "cash": "$0.00",
        "cashCents": 0,
        "callsBooked": 0,
        "callsHeld": 0,
        "noShow": 0,
        "noShowRate": "awaiting",
        "showed": 0,
        "showRate": "awaiting",
        "showRateNum": null,
        "closeRate": "awaiting",
        "closeRateNum": null,
        "outboundCalls": 3,
        "inboundCalls": 0,
        "totalCalls": 3,
        "callHours": 0.0,
        "trend": "flat",
        "trendNote": "flat vs prior period",
        "rank": 5
      }
    ],
    "month": [
      {
        "key": "caleb",
        "name": "Caleb Chase",
        "status": "active",
        "dealsClosed": 0,
        "cash": "$0.00",
        "cashCents": 0,
        "callsBooked": 65,
        "callsHeld": 0,
        "noShow": 20,
        "noShowRate": "56%",
        "showed": 16,
        "showRate": "44%",
        "showRateNum": 44.44444444444444,
        "closeRate": "0%",
        "closeRateNum": 0.0,
        "outboundCalls": 58,
        "inboundCalls": 8,
        "totalCalls": 66,
        "callHours": 1.5,
        "rank": 1,
        "trend": "down",
        "trendNote": "-$4,997.00, -1 deal"
      },
      {
        "key": "carlos",
        "name": "Carlos Fierro",
        "status": "active",
        "dealsClosed": 0,
        "cash": "$0.00",
        "cashCents": 0,
        "callsBooked": 39,
        "callsHeld": 1,
        "noShow": 6,
        "noShowRate": "50%",
        "showed": 6,
        "showRate": "50%",
        "showRateNum": 50.0,
        "closeRate": "0%",
        "closeRateNum": 0.0,
        "outboundCalls": 0,
        "inboundCalls": 0,
        "totalCalls": 0,
        "callHours": 0.0,
        "rank": 2,
        "trend": "flat",
        "trendNote": "flat vs prior period"
      },
      {
        "key": "james",
        "name": "James Wellington",
        "status": "active",
        "dealsClosed": 0,
        "cash": "$0.00",
        "cashCents": 0,
        "callsBooked": 0,
        "callsHeld": 0,
        "noShow": 0,
        "noShowRate": "awaiting",
        "showed": 0,
        "showRate": "awaiting",
        "showRateNum": null,
        "closeRate": "awaiting",
        "closeRateNum": null,
        "outboundCalls": 0,
        "inboundCalls": 0,
        "totalCalls": 0,
        "callHours": 0.0,
        "rank": 3,
        "trend": "flat",
        "trendNote": "flat vs prior period"
      },
      {
        "key": "dan",
        "name": "Dan Baldasso",
        "status": "offboarded",
        "dealsClosed": 0,
        "cash": "$0.00",
        "cashCents": 0,
        "callsBooked": 0,
        "callsHeld": 0,
        "noShow": 0,
        "noShowRate": "awaiting",
        "showed": 0,
        "showRate": "awaiting",
        "showRateNum": null,
        "closeRate": "awaiting",
        "closeRateNum": null,
        "outboundCalls": 22,
        "inboundCalls": 1,
        "totalCalls": 23,
        "callHours": 0.2,
        "trend": "flat",
        "trendNote": "flat vs prior period",
        "rank": 4
      },
      {
        "key": "matthew",
        "name": "Matthew Burns",
        "status": "offboarded",
        "dealsClosed": 0,
        "cash": "$0.00",
        "cashCents": 0,
        "callsBooked": 0,
        "callsHeld": 0,
        "noShow": 0,
        "noShowRate": "awaiting",
        "showed": 0,
        "showRate": "awaiting",
        "showRateNum": null,
        "closeRate": "awaiting",
        "closeRateNum": null,
        "outboundCalls": 8,
        "inboundCalls": 0,
        "totalCalls": 8,
        "callHours": 0.0,
        "trend": "flat",
        "trendNote": "flat vs prior period",
        "rank": 5
      }
    ],
    "quarter": [
      {
        "key": "caleb",
        "name": "Caleb Chase",
        "status": "active",
        "dealsClosed": 0,
        "cash": "$0.00",
        "cashCents": 0,
        "callsBooked": 65,
        "callsHeld": 0,
        "noShow": 20,
        "noShowRate": "56%",
        "showed": 16,
        "showRate": "44%",
        "showRateNum": 44.44444444444444,
        "closeRate": "0%",
        "closeRateNum": 0.0,
        "outboundCalls": 58,
        "inboundCalls": 8,
        "totalCalls": 66,
        "callHours": 1.5,
        "rank": 1,
        "trend": "down",
        "trendNote": "-$4,997.00, -1 deal"
      },
      {
        "key": "carlos",
        "name": "Carlos Fierro",
        "status": "active",
        "dealsClosed": 0,
        "cash": "$0.00",
        "cashCents": 0,
        "callsBooked": 39,
        "callsHeld": 1,
        "noShow": 6,
        "noShowRate": "50%",
        "showed": 6,
        "showRate": "50%",
        "showRateNum": 50.0,
        "closeRate": "0%",
        "closeRateNum": 0.0,
        "outboundCalls": 0,
        "inboundCalls": 0,
        "totalCalls": 0,
        "callHours": 0.0,
        "rank": 2,
        "trend": "flat",
        "trendNote": "flat vs prior period"
      },
      {
        "key": "james",
        "name": "James Wellington",
        "status": "active",
        "dealsClosed": 0,
        "cash": "$0.00",
        "cashCents": 0,
        "callsBooked": 0,
        "callsHeld": 0,
        "noShow": 0,
        "noShowRate": "awaiting",
        "showed": 0,
        "showRate": "awaiting",
        "showRateNum": null,
        "closeRate": "awaiting",
        "closeRateNum": null,
        "outboundCalls": 0,
        "inboundCalls": 0,
        "totalCalls": 0,
        "callHours": 0.0,
        "rank": 3,
        "trend": "flat",
        "trendNote": "flat vs prior period"
      },
      {
        "key": "dan",
        "name": "Dan Baldasso",
        "status": "offboarded",
        "dealsClosed": 0,
        "cash": "$0.00",
        "cashCents": 0,
        "callsBooked": 0,
        "callsHeld": 0,
        "noShow": 0,
        "noShowRate": "awaiting",
        "showed": 0,
        "showRate": "awaiting",
        "showRateNum": null,
        "closeRate": "awaiting",
        "closeRateNum": null,
        "outboundCalls": 22,
        "inboundCalls": 1,
        "totalCalls": 23,
        "callHours": 0.2,
        "trend": "flat",
        "trendNote": "flat vs prior period",
        "rank": 4
      },
      {
        "key": "matthew",
        "name": "Matthew Burns",
        "status": "offboarded",
        "dealsClosed": 0,
        "cash": "$0.00",
        "cashCents": 0,
        "callsBooked": 0,
        "callsHeld": 0,
        "noShow": 0,
        "noShowRate": "awaiting",
        "showed": 0,
        "showRate": "awaiting",
        "showRateNum": null,
        "closeRate": "awaiting",
        "closeRateNum": null,
        "outboundCalls": 8,
        "inboundCalls": 0,
        "totalCalls": 8,
        "callHours": 0.0,
        "trend": "flat",
        "trendNote": "flat vs prior period",
        "rank": 5
      }
    ],
    "allTime": [
      {
        "key": "caleb",
        "name": "Caleb Chase",
        "status": "active",
        "dealsClosed": 1,
        "cash": "$4,997.00",
        "cashCents": 499700,
        "callsBooked": 70,
        "callsHeld": 0,
        "noShow": 23,
        "noShowRate": "58%",
        "showed": 17,
        "showRate": "42%",
        "showRateNum": 42.5,
        "closeRate": "6%",
        "closeRateNum": 5.882352941176471,
        "outboundCalls": 68,
        "inboundCalls": 12,
        "totalCalls": 80,
        "callHours": 1.9,
        "rank": 1,
        "trend": "na",
        "trendNote": "since launch, no prior period"
      },
      {
        "key": "carlos",
        "name": "Carlos Fierro",
        "status": "active",
        "dealsClosed": 0,
        "cash": "$0.00",
        "cashCents": 0,
        "callsBooked": 49,
        "callsHeld": 2,
        "noShow": 8,
        "noShowRate": "50%",
        "showed": 8,
        "showRate": "50%",
        "showRateNum": 50.0,
        "closeRate": "0%",
        "closeRateNum": 0.0,
        "outboundCalls": 0,
        "inboundCalls": 0,
        "totalCalls": 0,
        "callHours": 0.0,
        "rank": 2,
        "trend": "na",
        "trendNote": "since launch, no prior period"
      },
      {
        "key": "james",
        "name": "James Wellington",
        "status": "active",
        "dealsClosed": 0,
        "cash": "$0.00",
        "cashCents": 0,
        "callsBooked": 0,
        "callsHeld": 0,
        "noShow": 0,
        "noShowRate": "awaiting",
        "showed": 0,
        "showRate": "awaiting",
        "showRateNum": null,
        "closeRate": "awaiting",
        "closeRateNum": null,
        "outboundCalls": 10,
        "inboundCalls": 0,
        "totalCalls": 10,
        "callHours": 0.0,
        "rank": 3,
        "trend": "na",
        "trendNote": "since launch, no prior period"
      },
      {
        "key": "dan",
        "name": "Dan Baldasso",
        "status": "offboarded",
        "dealsClosed": 0,
        "cash": "$0.00",
        "cashCents": 0,
        "callsBooked": 0,
        "callsHeld": 0,
        "noShow": 0,
        "noShowRate": "awaiting",
        "showed": 0,
        "showRate": "awaiting",
        "showRateNum": null,
        "closeRate": "awaiting",
        "closeRateNum": null,
        "outboundCalls": 30,
        "inboundCalls": 1,
        "totalCalls": 31,
        "callHours": 0.4,
        "trend": "na",
        "trendNote": "since launch, no prior period",
        "rank": 4
      },
      {
        "key": "matthew",
        "name": "Matthew Burns",
        "status": "offboarded",
        "dealsClosed": 0,
        "cash": "$0.00",
        "cashCents": 0,
        "callsBooked": 0,
        "callsHeld": 0,
        "noShow": 0,
        "noShowRate": "awaiting",
        "showed": 0,
        "showRate": "awaiting",
        "showRateNum": null,
        "closeRate": "awaiting",
        "closeRateNum": null,
        "outboundCalls": 9,
        "inboundCalls": 0,
        "totalCalls": 9,
        "callHours": 0.0,
        "trend": "na",
        "trendNote": "since launch, no prior period",
        "rank": 5
      }
    ]
  },
  "totals": {
    "day": {
      "dealsClosed": 0,
      "cash": "$0.00",
      "cashCents": 0,
      "callsBooked": 16,
      "callsHeld": 0,
      "noShow": 1,
      "noShowRate": "14%",
      "showed": 6,
      "showRate": "86%",
      "closeRate": "0%",
      "outboundCalls": 0,
      "inboundCalls": 0,
      "totalCalls": 0,
      "callHours": 0.0,
      "trend": "flat",
      "trendNote": "flat vs prior period"
    },
    "week": {
      "dealsClosed": 0,
      "cash": "$0.00",
      "cashCents": 0,
      "callsBooked": 95,
      "callsHeld": 0,
      "noShow": 22,
      "noShowRate": "54%",
      "showed": 19,
      "showRate": "46%",
      "closeRate": "0%",
      "outboundCalls": 61,
      "inboundCalls": 9,
      "totalCalls": 70,
      "callHours": 1.6,
      "trend": "down",
      "trendNote": "-$4,997.00, -1 deal"
    },
    "month": {
      "dealsClosed": 0,
      "cash": "$0.00",
      "cashCents": 0,
      "callsBooked": 104,
      "callsHeld": 1,
      "noShow": 26,
      "noShowRate": "54%",
      "showed": 22,
      "showRate": "46%",
      "closeRate": "0%",
      "outboundCalls": 88,
      "inboundCalls": 9,
      "totalCalls": 97,
      "callHours": 1.8,
      "trend": "down",
      "trendNote": "-$4,997.00, -1 deal"
    },
    "quarter": {
      "dealsClosed": 0,
      "cash": "$0.00",
      "cashCents": 0,
      "callsBooked": 104,
      "callsHeld": 1,
      "noShow": 26,
      "noShowRate": "54%",
      "showed": 22,
      "showRate": "46%",
      "closeRate": "0%",
      "outboundCalls": 88,
      "inboundCalls": 9,
      "totalCalls": 97,
      "callHours": 1.8,
      "trend": "down",
      "trendNote": "-$4,997.00, -1 deal"
    },
    "allTime": {
      "dealsClosed": 1,
      "cash": "$4,997.00",
      "cashCents": 499700,
      "callsBooked": 119,
      "callsHeld": 2,
      "noShow": 31,
      "noShowRate": "55%",
      "showed": 25,
      "showRate": "45%",
      "closeRate": "4%",
      "outboundCalls": 117,
      "inboundCalls": 13,
      "totalCalls": 130,
      "callHours": 2.3,
      "trend": "na",
      "trendNote": "since launch, no prior period"
    }
  },
  "activeTotals": {
    "day": {
      "dealsClosed": 0,
      "cash": "$0.00",
      "cashCents": 0,
      "callsBooked": 16,
      "callsHeld": 0,
      "noShow": 1,
      "noShowRate": "14%",
      "showed": 6,
      "showRate": "86%",
      "closeRate": "0%",
      "outboundCalls": 0,
      "inboundCalls": 0,
      "totalCalls": 0,
      "callHours": 0.0,
      "trend": "flat",
      "trendNote": "flat vs prior period"
    },
    "week": {
      "dealsClosed": 0,
      "cash": "$0.00",
      "cashCents": 0,
      "callsBooked": 95,
      "callsHeld": 0,
      "noShow": 22,
      "noShowRate": "54%",
      "showed": 19,
      "showRate": "46%",
      "closeRate": "0%",
      "outboundCalls": 43,
      "inboundCalls": 8,
      "totalCalls": 51,
      "callHours": 1.4,
      "trend": "down",
      "trendNote": "-$4,997.00, -1 deal"
    },
    "month": {
      "dealsClosed": 0,
      "cash": "$0.00",
      "cashCents": 0,
      "callsBooked": 104,
      "callsHeld": 1,
      "noShow": 26,
      "noShowRate": "54%",
      "showed": 22,
      "showRate": "46%",
      "closeRate": "0%",
      "outboundCalls": 58,
      "inboundCalls": 8,
      "totalCalls": 66,
      "callHours": 1.5,
      "trend": "down",
      "trendNote": "-$4,997.00, -1 deal"
    },
    "quarter": {
      "dealsClosed": 0,
      "cash": "$0.00",
      "cashCents": 0,
      "callsBooked": 104,
      "callsHeld": 1,
      "noShow": 26,
      "noShowRate": "54%",
      "showed": 22,
      "showRate": "46%",
      "closeRate": "0%",
      "outboundCalls": 58,
      "inboundCalls": 8,
      "totalCalls": 66,
      "callHours": 1.5,
      "trend": "down",
      "trendNote": "-$4,997.00, -1 deal"
    },
    "allTime": {
      "dealsClosed": 1,
      "cash": "$4,997.00",
      "cashCents": 499700,
      "callsBooked": 119,
      "callsHeld": 2,
      "noShow": 31,
      "noShowRate": "55%",
      "showed": 25,
      "showRate": "45%",
      "closeRate": "4%",
      "outboundCalls": 78,
      "inboundCalls": 12,
      "totalCalls": 90,
      "callHours": 1.9,
      "trend": "na",
      "trendNote": "since launch, no prior period"
    }
  },
  "leaders": {
    "day": {
      "topCash": null,
      "topCloseRate": {
        "key": "caleb",
        "name": "Caleb Chase",
        "value": "0%"
      },
      "topShowRate": {
        "key": "caleb",
        "name": "Caleb Chase",
        "value": "86%"
      },
      "mostActive": null,
      "topBooked": {
        "key": "caleb",
        "name": "Caleb Chase",
        "value": 10
      }
    },
    "week": {
      "topCash": null,
      "topCloseRate": {
        "key": "caleb",
        "name": "Caleb Chase",
        "value": "0%"
      },
      "topShowRate": {
        "key": "carlos",
        "name": "Carlos Fierro",
        "value": "50%"
      },
      "mostActive": {
        "key": "caleb",
        "name": "Caleb Chase",
        "value": 51
      },
      "topBooked": {
        "key": "caleb",
        "name": "Caleb Chase",
        "value": 63
      }
    },
    "month": {
      "topCash": null,
      "topCloseRate": {
        "key": "caleb",
        "name": "Caleb Chase",
        "value": "0%"
      },
      "topShowRate": {
        "key": "carlos",
        "name": "Carlos Fierro",
        "value": "50%"
      },
      "mostActive": {
        "key": "caleb",
        "name": "Caleb Chase",
        "value": 66
      },
      "topBooked": {
        "key": "caleb",
        "name": "Caleb Chase",
        "value": 65
      }
    },
    "quarter": {
      "topCash": null,
      "topCloseRate": {
        "key": "caleb",
        "name": "Caleb Chase",
        "value": "0%"
      },
      "topShowRate": {
        "key": "carlos",
        "name": "Carlos Fierro",
        "value": "50%"
      },
      "mostActive": {
        "key": "caleb",
        "name": "Caleb Chase",
        "value": 66
      },
      "topBooked": {
        "key": "caleb",
        "name": "Caleb Chase",
        "value": 65
      }
    },
    "allTime": {
      "topCash": {
        "key": "caleb",
        "name": "Caleb Chase",
        "value": "$4,997.00"
      },
      "topCloseRate": {
        "key": "caleb",
        "name": "Caleb Chase",
        "value": "6%"
      },
      "topShowRate": {
        "key": "carlos",
        "name": "Carlos Fierro",
        "value": "50%"
      },
      "mostActive": {
        "key": "caleb",
        "name": "Caleb Chase",
        "value": 80
      },
      "topBooked": {
        "key": "caleb",
        "name": "Caleb Chase",
        "value": 70
      }
    }
  },
  "daily": [
    {
      "date": "2026-06-15",
      "callsBooked": 3,
      "callsHeld": 0,
      "noShow": 0,
      "showed": 0,
      "won": 0,
      "cashCents": 0,
      "outboundCalls": 8,
      "inboundCalls": 0,
      "totalCalls": 8
    },
    {
      "date": "2026-06-16",
      "callsBooked": 0,
      "callsHeld": 0,
      "noShow": 0,
      "showed": 0,
      "won": 0,
      "cashCents": 0,
      "outboundCalls": 2,
      "inboundCalls": 0,
      "totalCalls": 2
    },
    {
      "date": "2026-06-17",
      "callsBooked": 0,
      "callsHeld": 0,
      "noShow": 0,
      "showed": 0,
      "won": 0,
      "cashCents": 0,
      "outboundCalls": 0,
      "inboundCalls": 0,
      "totalCalls": 0
    },
    {
      "date": "2026-06-18",
      "callsBooked": 0,
      "callsHeld": 0,
      "noShow": 0,
      "showed": 0,
      "won": 0,
      "cashCents": 0,
      "outboundCalls": 0,
      "inboundCalls": 0,
      "totalCalls": 0
    },
    {
      "date": "2026-06-19",
      "callsBooked": 0,
      "callsHeld": 0,
      "noShow": 0,
      "showed": 0,
      "won": 0,
      "cashCents": 0,
      "outboundCalls": 0,
      "inboundCalls": 0,
      "totalCalls": 0
    },
    {
      "date": "2026-06-20",
      "callsBooked": 0,
      "callsHeld": 0,
      "noShow": 0,
      "showed": 0,
      "won": 0,
      "cashCents": 0,
      "outboundCalls": 0,
      "inboundCalls": 0,
      "totalCalls": 0
    },
    {
      "date": "2026-06-21",
      "callsBooked": 0,
      "callsHeld": 0,
      "noShow": 0,
      "showed": 0,
      "won": 0,
      "cashCents": 0,
      "outboundCalls": 0,
      "inboundCalls": 0,
      "totalCalls": 0
    },
    {
      "date": "2026-06-22",
      "callsBooked": 2,
      "callsHeld": 0,
      "noShow": 0,
      "showed": 0,
      "won": 0,
      "cashCents": 0,
      "outboundCalls": 0,
      "inboundCalls": 0,
      "totalCalls": 0
    },
    {
      "date": "2026-06-23",
      "callsBooked": 0,
      "callsHeld": 0,
      "noShow": 0,
      "showed": 0,
      "won": 0,
      "cashCents": 0,
      "outboundCalls": 1,
      "inboundCalls": 0,
      "totalCalls": 1
    },
    {
      "date": "2026-06-24",
      "callsBooked": 1,
      "callsHeld": 0,
      "noShow": 0,
      "showed": 0,
      "won": 0,
      "cashCents": 0,
      "outboundCalls": 0,
      "inboundCalls": 0,
      "totalCalls": 0
    },
    {
      "date": "2026-06-25",
      "callsBooked": 0,
      "callsHeld": 0,
      "noShow": 0,
      "showed": 0,
      "won": 0,
      "cashCents": 0,
      "outboundCalls": 3,
      "inboundCalls": 0,
      "totalCalls": 3
    },
    {
      "date": "2026-06-26",
      "callsBooked": 0,
      "callsHeld": 0,
      "noShow": 0,
      "showed": 0,
      "won": 0,
      "cashCents": 0,
      "outboundCalls": 3,
      "inboundCalls": 3,
      "totalCalls": 6
    },
    {
      "date": "2026-06-27",
      "callsBooked": 0,
      "callsHeld": 0,
      "noShow": 0,
      "showed": 0,
      "won": 0,
      "cashCents": 0,
      "outboundCalls": 0,
      "inboundCalls": 0,
      "totalCalls": 0
    },
    {
      "date": "2026-06-28",
      "callsBooked": 2,
      "callsHeld": 0,
      "noShow": 1,
      "showed": 0,
      "won": 0,
      "cashCents": 0,
      "outboundCalls": 1,
      "inboundCalls": 0,
      "totalCalls": 1
    },
    {
      "date": "2026-06-29",
      "callsBooked": 2,
      "callsHeld": 1,
      "noShow": 1,
      "showed": 1,
      "won": 0,
      "cashCents": 0,
      "outboundCalls": 5,
      "inboundCalls": 0,
      "totalCalls": 5
    },
    {
      "date": "2026-06-30",
      "callsBooked": 5,
      "callsHeld": 0,
      "noShow": 3,
      "showed": 2,
      "won": 1,
      "cashCents": 499700,
      "outboundCalls": 6,
      "inboundCalls": 1,
      "totalCalls": 7
    },
    {
      "date": "2026-07-01",
      "callsBooked": 3,
      "callsHeld": 1,
      "noShow": 2,
      "showed": 1,
      "won": 0,
      "cashCents": 0,
      "outboundCalls": 13,
      "inboundCalls": 0,
      "totalCalls": 13
    },
    {
      "date": "2026-07-02",
      "callsBooked": 3,
      "callsHeld": 0,
      "noShow": 1,
      "showed": 2,
      "won": 0,
      "cashCents": 0,
      "outboundCalls": 10,
      "inboundCalls": 0,
      "totalCalls": 10
    },
    {
      "date": "2026-07-03",
      "callsBooked": 2,
      "callsHeld": 0,
      "noShow": 1,
      "showed": 0,
      "won": 0,
      "cashCents": 0,
      "outboundCalls": 1,
      "inboundCalls": 0,
      "totalCalls": 1
    },
    {
      "date": "2026-07-04",
      "callsBooked": 0,
      "callsHeld": 0,
      "noShow": 0,
      "showed": 0,
      "won": 0,
      "cashCents": 0,
      "outboundCalls": 0,
      "inboundCalls": 0,
      "totalCalls": 0
    },
    {
      "date": "2026-07-05",
      "callsBooked": 1,
      "callsHeld": 0,
      "noShow": 0,
      "showed": 0,
      "won": 0,
      "cashCents": 0,
      "outboundCalls": 3,
      "inboundCalls": 0,
      "totalCalls": 3
    },
    {
      "date": "2026-07-06",
      "callsBooked": 4,
      "callsHeld": 0,
      "noShow": 2,
      "showed": 0,
      "won": 0,
      "cashCents": 0,
      "outboundCalls": 7,
      "inboundCalls": 2,
      "totalCalls": 9
    },
    {
      "date": "2026-07-07",
      "callsBooked": 35,
      "callsHeld": 0,
      "noShow": 13,
      "showed": 5,
      "won": 0,
      "cashCents": 0,
      "outboundCalls": 15,
      "inboundCalls": 0,
      "totalCalls": 15
    },
    {
      "date": "2026-07-08",
      "callsBooked": 9,
      "callsHeld": 0,
      "noShow": 2,
      "showed": 2,
      "won": 0,
      "cashCents": 0,
      "outboundCalls": 10,
      "inboundCalls": 0,
      "totalCalls": 10
    },
    {
      "date": "2026-07-09",
      "callsBooked": 12,
      "callsHeld": 0,
      "noShow": 1,
      "showed": 4,
      "won": 0,
      "cashCents": 0,
      "outboundCalls": 14,
      "inboundCalls": 3,
      "totalCalls": 17
    },
    {
      "date": "2026-07-10",
      "callsBooked": 10,
      "callsHeld": 0,
      "noShow": 3,
      "showed": 2,
      "won": 0,
      "cashCents": 0,
      "outboundCalls": 14,
      "inboundCalls": 4,
      "totalCalls": 18
    },
    {
      "date": "2026-07-11",
      "callsBooked": 9,
      "callsHeld": 0,
      "noShow": 0,
      "showed": 0,
      "won": 0,
      "cashCents": 0,
      "outboundCalls": 1,
      "inboundCalls": 0,
      "totalCalls": 1
    },
    {
      "date": "2026-07-12",
      "callsBooked": 16,
      "callsHeld": 0,
      "noShow": 1,
      "showed": 6,
      "won": 0,
      "cashCents": 0,
      "outboundCalls": 0,
      "inboundCalls": 0,
      "totalCalls": 0
    }
  ],
  "dailyInsights": {
    "callsBookedNote": "119 calls booked since launch, 95 in the last 7 days. Busiest day: Jul 7 with 35.",
    "showRateNote": "Show rate has ranged 0% to 86% across the 12 days with a resolved call, averaging 40% recently.",
    "cashNote": "$4,997.00 collected total, entirely from one sale on Jun 30. No cash collected in the 12 days since.",
    "totalCallsBooked": 119,
    "bestDay": {
      "label": "Jul 7",
      "value": 35
    },
    "activeDays": 18,
    "totalDays": 28
  },
  "funnel": [
    {
      "key": "newUnworked",
      "label": "New, Unworked",
      "count": 97,
      "pct": "41%"
    },
    {
      "key": "contacted",
      "label": "Contacted",
      "count": 0,
      "pct": "0%"
    },
    {
      "key": "callBooked",
      "label": "Call Booked",
      "count": 47,
      "pct": "20%"
    },
    {
      "key": "rescheduling",
      "label": "Rescheduling",
      "count": 20,
      "pct": "8%"
    },
    {
      "key": "noShow",
      "label": "No Show",
      "count": 31,
      "pct": "13%"
    },
    {
      "key": "apptCancelled",
      "label": "Appt Cancelled",
      "count": 8,
      "pct": "3%"
    },
    {
      "key": "callHeld",
      "label": "Call Held",
      "count": 2,
      "pct": "1%"
    },
    {
      "key": "highPriority",
      "label": "High Priority",
      "count": 22,
      "pct": "9%"
    },
    {
      "key": "closedWon",
      "label": "Closed Won",
      "count": 1,
      "pct": "0%"
    },
    {
      "key": "longTermNurture",
      "label": "Long-Term Nurture",
      "count": 4,
      "pct": "2%"
    },
    {
      "key": "lost",
      "label": "Lost",
      "count": 7,
      "pct": "3%"
    }
  ],
  "funnelTotal": 239,
  "funnelInsights": {
    "leadNote": "97 of 239 opportunities (41%) are still New, Unworked.",
    "closeNote": "Of the 131 opportunities that reached Call Booked or further, 1 has closed (1%)."
  },
  "audit": {
    "excludedTestRecords": 4,
    "totalOpportunitiesPulled": 239,
    "nonCloserCallsAllTime": 108,
    "unattributedCashAllTime": "$0.00",
    "offboardedClosers": [
      "Matthew Burns",
      "Dan Baldasso"
    ],
    "offboardedCashAllTime": "$0.00",
    "offboardedDealsAllTime": 0
  }
}